phot/__init__.py
phot/components/__init__.py
phot/components/adaptive_equalizer.py
phot/components/ber.py
phot/components/bps.py
phot/components/dac_noise.py
phot/components/frame_syncer.py
phot/components/gaussian_noise.py
phot/components/modem.py
phot/components/phase_noise.py
phot/components/pulse_shaping.py
phot/components/rx_simple.py
phot/optical/__init__.py
phot/optical/awgn.py
phot/optical/bit_error.py
phot/optical/bps.py
phot/optical/cdc.py
phot/optical/cma_rde.py
phot/optical/dbp_compensate.py
phot/optical/fiber.py
phot/optical/fine_sync.py
phot/optical/linewidth_noise.py
phot/optical/offset_compens.py
phot/optical/orthog.py
phot/optical/resolution.py
phot/utils/__init__.py
phot/utils/dsp.py
phot/utils/gpu.py
phot/utils/io.py
phot/utils/logging.py
phot/utils/mathutils.py
phot/utils/plot.py
phot-0.2.12.dist-info/LICENSE
phot-0.2.12.dist-info/METADATA
phot-0.2.12.dist-info/WHEEL
phot-0.2.12.dist-info/top_level.txt
phot-0.2.12.dist-info/RECORD
