Metadata-Version: 2.1
Name: phot
Version: 0.2.12
Summary: A Python library for the simulation of optical fiber transmission
Home-page: https://github.com/phot-lab/pyphot
Author: Chunyu Li
Author-email: cyli0212@gmail.com
Requires-Python: >=3.7
License-File: LICENSE
Requires-Dist: matplotlib (>=3.5.2)
Requires-Dist: numba (>=0.55.2)
Requires-Dist: numpy (>=1.22.4)
Requires-Dist: scikit-commpy (>=0.7.0)
Requires-Dist: scipy (>=1.8.1)
